{
 "actions": [],
 "allow_rename": 1,
 "creation": "2024-10-09 18:20:10.879649",
 "doctype": "DocType",
 "editable_grid": 1,
 "engine": "InnoDB",
 "field_order": [
  "section_break_d0jr"
 ],
 "fields": [
  {
   "fieldname": "section_break_d0jr",
   "fieldtype": "Section Break"
  }
 ],
 "index_web_pages_for_search": 1,
 "istable": 1,
 "links": [],
 "modified": "2024-10-09 18:20:10.879649",
 "modified_by": "Administrator",
 "module": "mdm",
 "name": "Supplier Qualification Item",
 "owner": "Administrator",
 "permissions": [],
 "sort_field": "modified",
 "sort_order": "DESC",
 "states": []
}